thnkrSDK/__init__.py
thnkrSDK/thnkrSDK.py
thnkrSDK-0.0.7.dist-info/LICENSE
thnkrSDK-0.0.7.dist-info/METADATA
thnkrSDK-0.0.7.dist-info/WHEEL
thnkrSDK-0.0.7.dist-info/top_level.txt
thnkrSDK-0.0.7.dist-info/RECORD
