Metadata-Version: 2.1
Name: thnkrSDK
Version: 0.0.7
Summary: Software Development Kit for connecting to the thnkrAPI
Home-page: https://github.com/thnkrAI/thnkrSDK
Author: thnkrAI Inc.
Author-email: contact@thnkrai.com
Project-URL: Source, https://github.com/thnkrAI/thnkrSDK
Project-URL: Bug Reports, https://github.com/thnkrAI/thnkrSDK/issues
Classifier: License :: OSI Approved :: MIT License
Classifier: Programming Language :: Python :: 3
Classifier: Operating System :: OS Independent
Requires-Python: >=3.6
License-File: LICENSE
Requires-Dist: requests >=2.26.0
